{
  "version": "7",
  "dialect": "postgresql",
  "entries": [
    {
      "idx": 0,
      "version": "7",
      "when": 1774363230045,
      "tag": "0000_fresh_lily_hollister",
      "breakpoints": true
    },
    {
      "idx": 1,
      "version": "7",
      "when": 1774368253676,
      "tag": "0001_square_viper",
      "breakpoints": true
    },
    {
      "idx": 2,
      "version": "7",
      "when": 1774417000000,
      "tag": "0002_late_joseph",
      "breakpoints": true
    },
    {
      "idx": 3,
      "version": "7",
      "when": 1774503091777,
      "tag": "0003_clear_lifeguard",
      "breakpoints": true
    }
  ]
}